pykasacloud/__init__.py
pykasacloud/__version__.py
pykasacloud/const.py
pykasacloud/exceptions.py
pykasacloud/kasacloud.py
pykasacloud/py.typed
pykasacloud/protocols/__init__.py
pykasacloud/protocols/cloudprotocol.py
pykasacloud/transports/__init__.py
pykasacloud/transports/cloudtransport.py
pykasacloud-2025.9.1.dist-info/METADATA
pykasacloud-2025.9.1.dist-info/WHEEL
pykasacloud-2025.9.1.dist-info/licenses/LICENSE.txt
pykasacloud-2025.9.1.dist-info/RECORD
