Metadata-Version: 2.4
Name: pykasacloud
Version: 2025.9.1
Summary: Wrapper for python-kasa to connect with cloud devices.
Project-URL: Homepage, https://github.com/iluvdata/PyKasaCloud
Project-URL: Issues, https://github.com/iluvdata/PyKasaCloud/issues
Author-email: iluvdata <gbellsworth@gmail.com>
License-File: LICENSE.txt
Classifier: License :: OSI Approved :: MIT License
Classifier: Operating System :: OS Independent
Classifier: Programming Language :: Python :: 3
Classifier: Topic :: Home Automation
Requires-Python: >=3.9
Requires-Dist: python-kasa==0.10.2
